modmail/__init__.py
modmail-0.0.0a1.dist-info/WHEEL
modmail-0.0.0a1.dist-info/METADATA
modmail-0.0.0a1.dist-info/RECORD
