Metadata-Version: 2.1
Name: modmail
Version: 0.0.0a1
Summary: A modmail bot for Discord. Python 3.8+ compatible.
Home-page: https://discord-modmail.readthedocs.io
License: MIT
Keywords: modmail,discord,discord bot
Author: onerandomusername
Author-email: genericusername414@gmail.com
Requires-Python: >=3.8,<4.0
Classifier: Development Status :: 1 - Planning
Classifier: License :: OSI Approved :: MIT License
Classifier: Programming Language :: Python :: 3
Classifier: Programming Language :: Python :: 3.8
Classifier: Programming Language :: Python :: 3.9
Classifier: Programming Language :: Python :: 3.10
Project-URL: Repository, https://github.com/discord-modmail/modmail
